devModules/__init__.py
devModules/filesystem.py
devModules/manage_pi.py
devModules/piCommunication.py
devModules/piDev.py
remote_dev-0.1.3.dist-info/DESCRIPTION.rst
remote_dev-0.1.3.dist-info/METADATA
remote_dev-0.1.3.dist-info/RECORD
remote_dev-0.1.3.dist-info/WHEEL
remote_dev-0.1.3.dist-info/entry_points.txt
remote_dev-0.1.3.dist-info/metadata.json
remote_dev-0.1.3.dist-info/top_level.txt
scripts/__init__.py
scripts/echo_name.py
