Metadata-Version: 2.0
Name: remote-dev
Version: 0.1.3
Summary: package for automating running and developing on a remote server
Home-page: https://github.com/jaapjorisjaap/remote-dev/
Author: G.foks
Author-email: gerson.foks@gmail.com
License: Apache2
Platform: UNKNOWN
Classifier: Development Status :: 4 - Beta
Classifier: Programming Language :: Python :: 3
Requires-Dist: pyyaml
Requires-Dist: pathspec
